README.txt
setup.py
drupal_services/__init__.py
drupal_services/util.py
drupal_services.egg-info/PKG-INFO
drupal_services.egg-info/SOURCES.txt
drupal_services.egg-info/dependency_links.txt
drupal_services.egg-info/top_level.txt