Metadata-Version: 1.0
Name: drupal-services
Version: 0.1.0
Summary: Some simple Python classes for interacting with the Drupal 'services' module.
Home-page: UNKNOWN
Author: David Snopek
Author-email: dsnopek@gmail.com
License: MIT
Platform: UNKNOWN
Classifier: Development Status :: 3 - Alpha
Classifier: Topic :: Utilities
Classifier: License :: OSI Approved :: MIT License
